sdc_visualization/__init__.py
sdc_visualization/cli.py
sdc_visualization/sdc_visualization.py
sdc_visualization-0.1.0.dist-info/DESCRIPTION.rst
sdc_visualization-0.1.0.dist-info/METADATA
sdc_visualization-0.1.0.dist-info/RECORD
sdc_visualization-0.1.0.dist-info/WHEEL
sdc_visualization-0.1.0.dist-info/entry_points.txt
sdc_visualization-0.1.0.dist-info/metadata.json
sdc_visualization-0.1.0.dist-info/top_level.txt
