Metadata-Version: 2.0
Name: sdc-visualization
Version: 0.1.0
Summary: Visualisation tools and services for SeaDataCloud
Home-page: https://github.com/SiggyF/sdc_visualization
Author: Fedor Baart
Author-email: fedor.baart@deltares.nl
License: GNU General Public License v3
Keywords: sdc_visualization
Platform: UNKNOWN
Classifier: Development Status :: 2 - Pre-Alpha
Classifier: Intended Audience :: Developers
Classifier: License :: OSI Approved :: GNU General Public License v3 (GPLv3)
Classifier: Natural Language :: English
Classifier: Programming Language :: Python :: 3
Classifier: Programming Language :: Python :: 3.5
Classifier: Programming Language :: Python :: 3.6
Requires-Dist: Click (>=6.0)
